koine/__init__.py
koine/parser.py
koine-0.10.3.dist-info/licenses/LICENSE
koine-0.10.3.dist-info/METADATA
koine-0.10.3.dist-info/WHEEL
koine-0.10.3.dist-info/top_level.txt
koine-0.10.3.dist-info/RECORD
