Metadata-Version: 2.4
Name: koine
Version: 0.10.3
Summary: A declarative, data-driven parser generator for creating languages, ASTs, and transpilers.
Author-email: Chris Bates <1314008+chrsbats@users.noreply.github.com>
License-Expression: MIT
Project-URL: Homepage, https://github.com/chrsbats/koine
Project-URL: Bug Tracker, https://github.com/chrsbats/koine/issues
Classifier: Programming Language :: Python :: 3
Classifier: Programming Language :: Python :: 3 :: Only
Classifier: Programming Language :: Python :: 3.9
Classifier: Programming Language :: Python :: 3.10
Classifier: Programming Language :: Python :: 3.11
Classifier: Programming Language :: Python :: 3.12
Classifier: Programming Language :: Python :: 3.13
Classifier: Operating System :: OS Independent
Classifier: Topic :: Software Development :: Compilers
Classifier: Topic :: Text Processing :: General
Requires-Python: >=3.9
License-File: LICENSE
Requires-Dist: parsimonious
Requires-Dist: pyyaml
Provides-Extra: dev
Requires-Dist: pytest; extra == "dev"
Requires-Dist: pytest-cov; extra == "dev"
Dynamic: license-file
